glm_cli/__init__.py
glm_cli-0.1.0.dist-info/METADATA
glm_cli-0.1.0.dist-info/WHEEL
glm_cli-0.1.0.dist-info/entry_points.txt
glm_cli-0.1.0.dist-info/RECORD
