Metadata-Version: 2.3
Name: glm_cli
Version: 0.1.0
Summary: Genelec GLM API (works over virtual midi, expects app to be open)
Requires-Python: >=3.12
Requires-Dist: click>=8.1.7
Requires-Dist: mido>=1.3.2
Requires-Dist: python-rtmidi>=1.5.8
Provides-Extra: dev
Requires-Dist: pre-commit>=3.3.3; extra == 'dev'
Requires-Dist: pytest; extra == 'dev'
Requires-Dist: pytest-asyncio<0.23; extra == 'dev'
Requires-Dist: pytest-cov; extra == 'dev'
Requires-Dist: ruff>=0.6.3; extra == 'dev'
Provides-Extra: release
Requires-Dist: twine; extra == 'release'
